{"56": {"state": "Wyoming", "abbrev": "WY"}, "54": {"state": "West Virginia", "abbrev": "WV"}, "42": {"state": "Pennsylvania", "abbrev": "PA"}, "50": {"state": "Vermont", "abbrev": "VT"}, "49": {"state": "Utah", "abbrev": "UT"}, "53": {"state": "Washington", "abbrev": "WA"}, "24": {"state": "Maryland", "abbrev": "MD"}, "25": {"state": "Massachusetts", "abbrev": "MA"}, "26": {"state": "Michigan", "abbrev": "MI"}, "27": {"state": "Minnesota", "abbrev": "MN"}, "20": {"state": "Kansas", "abbrev": "KS"}, "21": {"state": "Kentucky", "abbrev": "KY"}, "22": {"state": "Louisiana", "abbrev": "LA"}, "23": {"state": "Maine", "abbrev": "ME"}, "46": {"state": "South Dakota", "abbrev": "SD"}, "47": {"state": "Tennessee", "abbrev": "TN"}, "44": {"state": "Rhode Island", "abbrev": "RI"}, "45": {"state": "South Carolina", "abbrev": "SC"}, "28": {"state": "Mississippi", "abbrev": "MS"}, "29": {"state": "Missouri", "abbrev": "MO"}, "40": {"state": "Oklahoma", "abbrev": "OK"}, "41": {"state": "Oregon", "abbrev": "OR"}, "1": {"state": "Alabama", "abbrev": "AL"}, "2": {"state": "Alaska", "abbrev": "AK"}, "5": {"state": "Arkansas", "abbrev": "AR"}, "4": {"state": "Arizona", "abbrev": "AZ"}, "6": {"state": "California", "abbrev": "CA"}, "9": {"state": "Connecticut", "abbrev": "CT"}, "8": {"state": "Colorado", "abbrev": "CO"}, "51": {"state": "Virginia", "abbrev": "VA"}, "39": {"state": "Ohio", "abbrev": "OH"}, "38": {"state": "North Dakota", "abbrev": "ND"}, "11": {"state": "District of Columbia", "abbrev": "DC"}, "10": {"state": "Delaware", "abbrev": "DE"}, "13": {"state": "Georgia", "abbrev": "GA"}, "12": {"state": "Florida", "abbrev": "FL"}, "15": {"state": "Hawaii", "abbrev": "HI"}, "48": {"state": "Texas", "abbrev": "TX"}, "17": {"state": "Illinois", "abbrev": "IL"}, "16": {"state": "Idaho", "abbrev": "ID"}, "19": {"state": "Iowa", "abbrev": "IA"}, "18": {"state": "Indiana", "abbrev": "IN"}, "31": {"state": "Nebraska", "abbrev": "NE"}, "30": {"state": "Montana", "abbrev": "MT"}, "37": {"state": "North Carolina", "abbrev": "NC"}, "36": {"state": "New York", "abbrev": "NY"}, "35": {"state": "New Mexico", "abbrev": "NM"}, "34": {"state": "New Jersey", "abbrev": "NJ"}, "33": {"state": "New Hampshire", "abbrev": "NH"}, "55": {"state": "Wisconsin", "abbrev": "WI"}, "32": {"state": "Nevada", "abbrev": "NV"}}